Metadata-Version: 2.1
Name: bxss-sniper
Version: 1.0.0
Summary: Bxss Sniper: A web application penetration testing tool for Blind XSS detection
Author: D. Sanjai Kumar
Author-email: bughunterz0047@gmail.com
